DensityPlot/__init__.py
DensityPlot/plot.py
DensityPlot-0.1.8.dist-info/LICENSE
DensityPlot-0.1.8.dist-info/METADATA
DensityPlot-0.1.8.dist-info/WHEEL
DensityPlot-0.1.8.dist-info/top_level.txt
DensityPlot-0.1.8.dist-info/RECORD
