Metadata-Version: 2.1
Name: DensityPlot
Version: 0.1.8
Summary: A simple density plotting tool for FACS-like data.
Home-page: https://github.com/xuesoso/DensityPlot
Author: YSX
Author-email: xuesoso@gmail.com
License: LICENSE
Platform: UNKNOWN
Requires-Dist: scipy (>=0.14.0)
Requires-Dist: matplotlib (>=2.0.0)
